cohens_d/__init__.py
cohens_d/__version__.py
cohens_d/core.py
cohens_d_effect_size-1.2.0.dist-info/licenses/LICENSE
cohens_d_effect_size-1.2.0.dist-info/METADATA
cohens_d_effect_size-1.2.0.dist-info/WHEEL
cohens_d_effect_size-1.2.0.dist-info/top_level.txt
cohens_d_effect_size-1.2.0.dist-info/RECORD
