Metadata-Version: 2.4
Name: cohens-d-effect-size
Version: 1.2.0
Summary: A Python package for calculating Cohen's d effect size
Home-page: https://github.com/DawitLam/cohens-d
Author: Dawit L. Gulta
Author-email: "Dawit L. Gulta" <dawit.lambebo@gmail.com>
License: BSD 3-Clause License
Project-URL: Homepage, https://github.com/DawitLam/cohens-d-scipy
Project-URL: Documentation, https://github.com/DawitLam/cohens-d-scipy#readme
Project-URL: Repository, https://github.com/DawitLam/cohens-d-scipy.git
Project-URL: Bug Tracker, https://github.com/DawitLam/cohens-d-scipy/issues
Keywords: cohen's d,effect size,statistics,research,psychology,data science
Classifier: Development Status :: 4 - Beta
Classifier: Intended Audience :: Science/Research
Classifier: Intended Audience :: Education
Classifier: License :: OSI Approved :: BSD License
Classifier: Operating System :: OS Independent
Classifier: Programming Language :: Python :: 3
Classifier: Programming Language :: Python :: 3.8
Classifier: Programming Language :: Python :: 3.9
Classifier: Programming Language :: Python :: 3.10
Classifier: Programming Language :: Python :: 3.11
Classifier: Programming Language :: Python :: 3.12
Classifier: Topic :: Scientific/Engineering :: Mathematics
Classifier: Topic :: Scientific/Engineering :: Information Analysis
Classifier: Topic :: Education
Classifier: Typing :: Typed
Requires-Python: >=3.8
License-File: LICENSE
Requires-Dist: numpy>=1.19.0
Provides-Extra: dev
Requires-Dist: pytest>=6.0; extra == "dev"
Requires-Dist: pytest-cov; extra == "dev"
Requires-Dist: black; extra == "dev"
Requires-Dist: flake8; extra == "dev"
Requires-Dist: mypy; extra == "dev"
Requires-Dist: build; extra == "dev"
Requires-Dist: twine; extra == "dev"
Provides-Extra: test
Requires-Dist: pytest>=6.0; extra == "test"
Requires-Dist: pytest-cov; extra == "test"
Dynamic: author
Dynamic: home-page
Dynamic: license-file
Dynamic: requires-python
